lookoutequipment/__init__.py
lookoutequipment/dataset.py
lookoutequipment/evaluation.py
lookoutequipment/model.py
lookoutequipment/plot.py
lookoutequipment/scheduler.py
lookoutequipment/schema.py
lookoutequipment-0.1.5.dist-info/LICENSE
lookoutequipment-0.1.5.dist-info/METADATA
lookoutequipment-0.1.5.dist-info/NOTICE
lookoutequipment-0.1.5.dist-info/WHEEL
lookoutequipment-0.1.5.dist-info/top_level.txt
lookoutequipment-0.1.5.dist-info/RECORD
