Metadata-Version: 2.1
Name: lookoutequipment
Version: 0.1.5
Summary: Python SDK for Amazon Lookout for Equipment
Home-page: https://github.com/aws-samples/amazon-lookout-for-equipment-python-sdk
Author: Michael Hoarau
Author-email: michoara@amazon.com
License: Apache-2.0
Platform: UNKNOWN
License-File: LICENSE
License-File: NOTICE
Requires-Dist: awswrangler
Requires-Dist: tqdm
Requires-Dist: markdown
